webdiff/__init__.py
webdiff/app.py
webdiff/argparser.py
webdiff/diff.py
webdiff/dirdiff.py
webdiff/github_fetcher.py
webdiff/githubdiff.py
webdiff/gitwebdiff.py
webdiff/gitwebshow.py
webdiff/localfilediff.py
webdiff/options.py
webdiff/static/__init__.py
webdiff/static/codediff.js/codediff.css
webdiff/static/codediff.js/googlecode.css
webdiff/static/css/Inconsolata/Inconsolata-Bold.ttf
webdiff/static/css/Inconsolata/Inconsolata-Regular.ttf
webdiff/static/css/Inconsolata/OFL.txt
webdiff/static/css/googlecode.css
webdiff/static/css/inconsolata.css
webdiff/static/css/style.css
webdiff/static/css/themes/a11y-dark.css
webdiff/static/css/themes/a11y-light.css
webdiff/static/css/themes/agate.css
webdiff/static/css/themes/an-old-hope.css
webdiff/static/css/themes/androidstudio.css
webdiff/static/css/themes/arduino-light.css
webdiff/static/css/themes/arta.css
webdiff/static/css/themes/ascetic.css
webdiff/static/css/themes/atom-one-dark-reasonable.css
webdiff/static/css/themes/atom-one-dark.css
webdiff/static/css/themes/atom-one-light.css
webdiff/static/css/themes/base16/3024.css
webdiff/static/css/themes/base16/apathy.css
webdiff/static/css/themes/base16/apprentice.css
webdiff/static/css/themes/base16/ashes.css
webdiff/static/css/themes/base16/atelier-cave-light.css
webdiff/static/css/themes/base16/atelier-cave.css
webdiff/static/css/themes/base16/atelier-dune-light.css
webdiff/static/css/themes/base16/atelier-dune.css
webdiff/static/css/themes/base16/atelier-estuary-light.css
webdiff/static/css/themes/base16/atelier-estuary.css
webdiff/static/css/themes/base16/atelier-forest-light.css
webdiff/static/css/themes/base16/atelier-forest.css
webdiff/static/css/themes/base16/atelier-heath-light.css
webdiff/static/css/themes/base16/atelier-heath.css
webdiff/static/css/themes/base16/atelier-lakeside-light.css
webdiff/static/css/themes/base16/atelier-lakeside.css
webdiff/static/css/themes/base16/atelier-plateau-light.css
webdiff/static/css/themes/base16/atelier-plateau.css
webdiff-1.3.0.dist-info/LICENSE
webdiff-1.3.0.dist-info/METADATA
webdiff-1.3.0.dist-info/WHEEL
webdiff-1.3.0.dist-info/entry_points.txt
webdiff-1.3.0.dist-info/RECORD
