Metadata-Version: 2.1
Name: webdiff
Version: 1.3.0
Summary: Two-column web-based git difftool
Home-page: https://github.com/danvk/webdiff/
License: Apache-2.0
Keywords: git,difftool,web
Author: Dan Vanderkam
Author-email: danvdk@gmail.com
Requires-Python: >=3.10,<4.0
Classifier: Development Status :: 4 - Beta
Classifier: Environment :: Console
Classifier: Environment :: Web Environment
Classifier: Intended Audience :: Developers
Classifier: License :: OSI Approved :: Apache Software License
Classifier: Programming Language :: Python :: 3
Classifier: Programming Language :: Python :: 3.10
Classifier: Programming Language :: Python :: 3.11
Classifier: Programming Language :: Python :: 3.12
Classifier: Topic :: Software Development :: Version Control
Requires-Dist: PyGithub (>=2.3.0,<3.0.0)
Requires-Dist: aiohttp (>=3.9.5,<4.0.0)
Requires-Dist: binaryornot
Requires-Dist: pillow
Requires-Dist: unidiff (>=0.7.4,<0.8.0)
Project-URL: Repository, https://github.com/danvk/webdiff/
